MANIFEST.in
setup.py
django_project.egg-info/PKG-INFO
django_project.egg-info/SOURCES.txt
django_project.egg-info/dependency_links.txt
django_project.egg-info/requires.txt
django_project.egg-info/top_level.txt
project/__init__.py
project/bin/django-project.py
project/management/__init__.py
project/management/commands/__init__.py
project/management/commands/installapp.py
project/management/commands/startproject.py
project/management/commands/uninstallapp.py
project/template/__init__.py
project/template/media/README.txt
project/template/source/__init__.py
project/template/source/__init__.pyc
project/template/source/manage.py
project/template/source/settings.py
project/template/source/settings.pyc
project/template/source/urls.py
project/template/source/urls.pyc
project/template/source/apps/__init__.py
project/template/source/apps/ext/__init__.py
project/template/source/apps/web/__init__.py
project/template/source/apps/web/__init__.pyc
project/template/source/apps/web/context_processors.py
project/template/source/apps/web/decorators.py
project/template/source/apps/web/middleware.py
project/template/source/apps/web/models.py
project/template/source/apps/web/models.pyc
project/template/source/apps/web/urls.py
project/template/source/apps/web/urls.pyc
project/template/source/apps/web/views.py
project/template/source/apps/web/views.pyc
project/template/source/apps/web/templates/web/base.html
project/template/source/apps/web/templatetags/__init__.py
project/template/source/apps/web/templatetags/__init__.pyc
project/template/source/conf/__init__.py
project/template/source/conf/__init__.pyc
project/template/source/conf/apps/__init__.py
project/template/source/conf/apps/__init__.pyc
project/template/source/conf/apps/admin/__init__.py
project/template/source/conf/apps/admin/__init__.pyc
project/template/source/conf/apps/admin/urls.py
project/template/source/conf/apps/admin/urls.pyc
project/template/source/conf/apps/web/__init__.py
project/template/source/conf/apps/web/__init__.pyc
project/template/source/conf/apps/web/settings.py
project/template/source/conf/apps/web/settings.pyc
project/template/source/conf/apps/web/staticfinders.py
