Metadata-Version: 1.0
Name: django-project
Version: 0.7
Summary: Modular & scalable Django project template
Home-page: http://github.com/kottenator/django-project
Author: Rostyslav Bryzgunov
Author-email: kottenator@gmail.com
License: MIT
Platform: UNKNOWN
Classifier: Framework :: Django
Classifier: Intended Audience :: Developers
Classifier: Intended Audience :: System Administrators
Classifier: Operating System :: OS Independent
Classifier: Topic :: Software Development
